{"2024-06-24-2024-06-24": {"VEN - Medios adversos - FB": [{"valor": 43, "palabra": "estados-unidos"}, {"valor": 31, "palabra": "corina-machado"}, {"valor": 29, "palabra": "edmundo-gonzález"}, {"valor": 29, "palabra": "amplía-detalles"}, {"valor": 29, "palabra": "edmundo-presidente"}, {"valor": 24, "palabra": "nicolás-maduro"}, {"valor": 20, "palabra": "nuestra-página"}, {"valor": 17, "palabra": "noticias-nuestra"}, {"valor": 16, "palabra": "millones-dólares"}, {"valor": 15, "palabra": "gonzález-urrutia"}, {"valor": 15, "palabra": "cantar-fraude"}, {"valor": 12, "palabra": "gregorio-hernández"}, {"valor": 12, "palabra": "fuerzas-armadas"}, {"valor": 11, "palabra": "batalla-carabobo"}, {"valor": 11, "palabra": "corina-cantar"}, {"valor": 9, "palabra": "elecciones-presidenciales"}, {"valor": 9, "palabra": "tráfico-personas"}, {"valor": 9, "palabra": "segunda-marquetalia"}, {"valor": 9, "palabra": "general-pueblo"}, {"valor": 8, "palabra": "fuerza-armada"}, {"valor": 8, "palabra": "orlando-utrera"}, {"valor": 8, "palabra": "pueblo-venezolano"}, {"valor": 8, "palabra": "eduardo-serrano"}, {"valor": 7, "palabra": "campaña-electoral"}, {"valor": 7, "palabra": "selección-colombia"}, {"valor": 7, "palabra": "colombia-américa"}, {"valor": 7, "palabra": "quiere-volver"}, {"valor": 6, "palabra": "urrutia-presidente"}, {"valor": 6, "palabra": "armada-nacional"}, {"valor": 6, "palabra": "departamento-estado"}], "VEN - Medios afines - FB": [{"valor": 31, "palabra": "batalla-carabobo"}, {"valor": 25, "palabra": "edmundo-gonzález"}, {"valor": 20, "palabra": "nicolás-maduro"}, {"valor": 16, "palabra": "edmundo-presidente"}, {"valor": 16, "palabra": "jajajaja-jajajaja"}, {"valor": 16, "palabra": "ingresa-nuestro"}, {"valor": 16, "palabra": "nuestro-perfil"}, {"valor": 15, "palabra": "corina-machado"}, {"valor": 12, "palabra": "segunda-marquetalia"}, {"valor": 9, "palabra": "pueblo-venezolano"}, {"valor": 9, "palabra": "información-ingresa"}, {"valor": 8, "palabra": "jajaja-jajaja"}, {"valor": 7, "palabra": "gobierno-colombia"}, {"valor": 7, "palabra": "colombia-segunda"}, {"valor": 6, "palabra": "hablemos-infraestructuras"}, {"valor": 6, "palabra": "infraestructuras-empezó"}, {"valor": 6, "palabra": "empezó-chávez"}, {"valor": 6, "palabra": "chávez-trenes"}, {"valor": 6, "palabra": "trenes-llegaron"}, {"valor": 6, "palabra": "llegaron-puentes"}, {"valor": 6, "palabra": "puentes-construyeron"}, {"valor": 6, "palabra": "construyeron-centrales"}, {"valor": 6, "palabra": "centrales-hidroeléctricas"}, {"valor": 6, "palabra": "hidroeléctricas-arrancaron"}, {"valor": 6, "palabra": "arrancaron-dinero"}, {"valor": 6, "palabra": "dinero-desapareció"}, {"valor": 6, "palabra": "desapareció-hablemos"}, {"valor": 6, "palabra": "hablemos-estaban"}, {"valor": 6, "palabra": "estaban-chávez"}, {"valor": 6, "palabra": "chávez-hospitales"}], "VEN - Figuras afines - Ministros FB": [{"valor": 3, "palabra": "impulsar-turismo"}, {"valor": 2, "palabra": "batalla-carabobo"}, {"valor": 2, "palabra": "aniversario-batalla"}, {"valor": 2, "palabra": "programa-maduro"}, {"valor": 2, "palabra": "apóyenos-impulsar"}, {"valor": 2, "palabra": "turismo-nuestro"}, {"valor": 2, "palabra": "nuestro-municipio"}, {"valor": 1, "palabra": "internacional-incluyó"}, {"valor": 1, "palabra": "incluyó-programación"}, {"valor": 1, "palabra": "programación-espacio"}, {"valor": 1, "palabra": "espacio-solidaridad"}, {"valor": 1, "palabra": "solidaridad-julián"}, {"valor": 1, "palabra": "julián-assange"}, {"valor": 1, "palabra": "assange-albaciudadorg202011ellla"}, {"valor": 1, "palabra": "albaciudadorg202011ellla-minúsculo"}, {"valor": 1, "palabra": "minúsculo-granito"}, {"valor": 1, "palabra": "granito-mundial"}, {"valor": 1, "palabra": "mundial-libertad"}, {"valor": 1, "palabra": "libertad-realidad"}, {"valor": 1, "palabra": "realidad-enhorabuena"}, {"valor": 1, "palabra": "enhorabuena-curiepe"}, {"valor": 1, "palabra": "curiepe-primer"}, {"valor": 1, "palabra": "primer-pueblo"}, {"valor": 1, "palabra": "pueblo-negros"}, {"valor": 1, "palabra": "negros-libres"}, {"valor": 1, "palabra": "libres-bautista"}, {"valor": 1, "palabra": "bautista-equipo"}, {"valor": 1, "palabra": "equipo-promotor"}, {"valor": 1, "palabra": "promotor-nacional"}, {"valor": 1, "palabra": "nacional-misión"}], "VEN - Nicolás Maduro - FB": [{"valor": 94, "palabra": "nicolás-maduro"}, {"valor": 50, "palabra": "presidente-nicolás"}, {"valor": 29, "palabra": "saludos-presidente"}, {"valor": 28, "palabra": "presidente-maduro"}, {"valor": 23, "palabra": "nicolas-maduro"}, {"valor": 22, "palabra": "edmundo-corina"}, {"valor": 19, "palabra": "presidente-obrero"}, {"valor": 17, "palabra": "maduro-presidente"}, {"valor": 17, "palabra": "victoria-siempre"}, {"valor": 17, "palabra": "castigo-castigo"}, {"valor": 15, "palabra": "aumento-presidente"}, {"valor": 13, "palabra": "edmundo-presidente"}, {"valor": 13, "palabra": "buenas-noches"}, {"valor": 13, "palabra": "nuestro-presidente"}, {"valor": 12, "palabra": "obrero-aumento"}, {"valor": 12, "palabra": "presidente-nicolas"}, {"valor": 11, "palabra": "pueblo-venezolano"}, {"valor": 11, "palabra": "maduro-venceremos"}, {"valor": 10, "palabra": "batalla-carabobo"}, {"valor": 10, "palabra": "bendiciones-presidente"}, {"valor": 10, "palabra": "venceremos-presidente"}, {"valor": 9, "palabra": "siempre-presidente"}, {"valor": 9, "palabra": "nuestra-patria"}, {"valor": 9, "palabra": "bendiga-siempre"}, {"valor": 9, "palabra": "palante-presidente"}, {"valor": 9, "palabra": "revolución-bolivariana"}, {"valor": 8, "palabra": "presidente-presidente"}, {"valor": 8, "palabra": "maduro-venezuela"}, {"valor": 8, "palabra": "presidente-victoria"}, {"valor": 8, "palabra": "maduro-palante"}], "VEN - Figuras opositoras - FB": [{"valor": 19, "palabra": "muchas-felicidades"}, {"valor": 16, "palabra": "bendiciones-cumpleaños"}, {"valor": 13, "palabra": "muchas-bendiciones"}, {"valor": 13, "palabra": "felicidades-bendiciones"}, {"valor": 11, "palabra": "cumpleaños-bendiga"}, {"valor": 8, "palabra": "bendiga-siempre"}, {"valor": 7, "palabra": "cumpleaños-muchas"}, {"valor": 7, "palabra": "bendiciones-felicidades"}, {"valor": 7, "palabra": "cumpleaños-cumpleaños"}, {"valor": 6, "palabra": "cumpleaños-bendiciones"}, {"valor": 6, "palabra": "bendiciones-muchas"}, {"valor": 6, "palabra": "felicidades-cumpleaños"}, {"valor": 5, "palabra": "cumpla-muchos"}, {"valor": 5, "palabra": "siempre-muchas"}, {"valor": 5, "palabra": "felicidades-muchas"}, {"valor": 4, "palabra": "lluvia-bendiciones"}, {"valor": 4, "palabra": "felicitaciones-cumpleaños"}, {"valor": 4, "palabra": "cumpleaños-hermosa"}, {"valor": 4, "palabra": "felicitaciones-bendiciones"}, {"valor": 4, "palabra": "cumpleaños-señora"}, {"valor": 4, "palabra": "felicidades-felicidades"}, {"valor": 4, "palabra": "felicidades-felicitaciones"}, {"valor": 3, "palabra": "bendiciones-familia"}, {"valor": 3, "palabra": "cumpleaños-felicidades"}, {"valor": 3, "palabra": "muchos-cumpleaños"}, {"valor": 3, "palabra": "infinitas-bendiciones"}, {"valor": 3, "palabra": "bendiga-muchos"}, {"valor": 3, "palabra": "siempre-bendiga"}, {"valor": 3, "palabra": "felicidades-cumpla"}, {"valor": 3, "palabra": "bendiga-grandemente"}], "VEN - CORINA MACHADO - FB": [{"valor": 2, "palabra": "bendiga-corina"}, {"valor": 2, "palabra": "edmundo-presidente"}, {"valor": 2, "palabra": "victoria-libertad"}, {"valor": 2, "palabra": "hombre-confia"}, {"valor": 2, "palabra": "ejército-patriota"}, {"valor": 2, "palabra": "carabobo-carabobo"}, {"valor": 2, "palabra": "corina-machado"}, {"valor": 1, "palabra": "control-hierro"}, {"valor": 1, "palabra": "hierro-cuídate"}, {"valor": 1, "palabra": "cuídate-bendiga"}, {"valor": 1, "palabra": "corina-corina"}, {"valor": 1, "palabra": "corina-preocupe"}, {"valor": 1, "palabra": "preocupe-nombró"}, {"valor": 1, "palabra": "nombró-amoroso"}, {"valor": 1, "palabra": "amoroso-seremos"}, {"valor": 1, "palabra": "seremos-testigos"}, {"valor": 1, "palabra": "testigos-estamos"}, {"valor": 1, "palabra": "estamos-maduro"}, {"valor": 1, "palabra": "maduro-defenderemos"}, {"valor": 1, "palabra": "defenderemos-edmundo"}, {"valor": 1, "palabra": "presidente-duelale"}, {"valor": 1, "palabra": "duelale-vamoooos"}, {"valor": 1, "palabra": "vamoooos-carajoooooooo"}, {"valor": 1, "palabra": "carajoooooooo-venezuela"}, {"valor": 1, "palabra": "venezuela-libertadpide"}, {"valor": 1, "palabra": "libertadpide-justicia"}, {"valor": 1, "palabra": "justicia-hagamos"}, {"valor": 1, "palabra": "hagamos-historiaesta"}, {"valor": 1, "palabra": "historiaesta-protejala"}, {"valor": 1, "palabra": "protejala-celebraré"}]}, "2024-06-25-2024-06-25": {"VEN - Medios adversos - FB": [{"valor": 33, "palabra": "edmundo-presidente"}, {"valor": 33, "palabra": "jajajaja-jajajaja"}, {"valor": 31, "palabra": "edmundo-gonzález"}, {"valor": 31, "palabra": "corina-machado"}, {"valor": 29, "palabra": "nicolás-maduro"}, {"valor": 26, "palabra": "sistema-eléctrico"}, {"valor": 24, "palabra": "estados-unidos"}, {"valor": 24, "palabra": "cantar-fraude"}, {"valor": 21, "palabra": "amplía-detalles"}, {"valor": 20, "palabra": "elecciones-presidenciales"}, {"valor": 18, "palabra": "gregorio-hernández"}, {"valor": 18, "palabra": "corina-cantar"}, {"valor": 15, "palabra": "julian-assange"}, {"valor": 12, "palabra": "proceso-electoral"}, {"valor": 10, "palabra": "gonzález-urrutia"}, {"valor": 9, "palabra": "fuerzas-armadas"}, {"valor": 9, "palabra": "pueblo-venezuela"}, {"valor": 8, "palabra": "consejo-nacional"}, {"valor": 8, "palabra": "secretario-general"}, {"valor": 8, "palabra": "canonización-gregorio"}, {"valor": 8, "palabra": "olvides-suscribirte"}, {"valor": 7, "palabra": "nacional-electoral"}, {"valor": 7, "palabra": "expertos-electorales"}, {"valor": 7, "palabra": "derechos-humanos"}, {"valor": 7, "palabra": "primer-puesto"}, {"valor": 7, "palabra": "juegos-olímpicos"}, {"valor": 7, "palabra": "michael-jackson"}, {"valor": 7, "palabra": "pueblo-quiere"}, {"valor": 7, "palabra": "humillante-derrota"}, {"valor": 7, "palabra": "derrota-edmundo"}], "VEN - Medios afines - FB": [{"valor": 70, "palabra": "edmundo-presidente"}, {"valor": 63, "palabra": "edmundo-gonzález"}, {"valor": 39, "palabra": "nicolás-maduro"}, {"valor": 31, "palabra": "pueblo-venezolano"}, {"valor": 26, "palabra": "corina-machado"}, {"valor": 17, "palabra": "fuerzas-armadas"}, {"valor": 17, "palabra": "fuerza-armada"}, {"valor": 15, "palabra": "julian-assange"}, {"valor": 15, "palabra": "estados-unidos"}, {"valor": 14, "palabra": "gonzález-urrutia"}, {"valor": 14, "palabra": "presidente-nicolás"}, {"valor": 14, "palabra": "corina-edmundo"}, {"valor": 14, "palabra": "presidente-venezuela"}, {"valor": 13, "palabra": "presidente-maduro"}, {"valor": 13, "palabra": "presidente-edmundo"}, {"valor": 12, "palabra": "millones-dólares"}, {"valor": 11, "palabra": "elecciónes-presidenciales"}, {"valor": 11, "palabra": "elecciones-presidenciales"}, {"valor": 11, "palabra": "maduro-edmundo"}, {"valor": 11, "palabra": "venezuela-maduro"}, {"valor": 11, "palabra": "venezuela-edmundo"}, {"valor": 11, "palabra": "jajajaja-jajajaja"}, {"valor": 10, "palabra": "valides-porque"}, {"valor": 10, "palabra": "triunfo-edmundo"}, {"valor": 10, "palabra": "pueblo-venezuela"}, {"valor": 10, "palabra": "nicolas-maduro"}, {"valor": 9, "palabra": "delincuente-colombiano"}, {"valor": 9, "palabra": "gregorio-hernández"}, {"valor": 8, "palabra": "diosdado-cabello"}, {"valor": 8, "palabra": "julián-assange"}], "VEN - Figuras afines - Ministros FB": [{"valor": 2, "palabra": "vuelve-turpial"}, {"valor": 2, "palabra": "rafael-urdaneta"}, {"valor": 2, "palabra": "buenas-tardes"}, {"valor": 2, "palabra": "tardes-presidente"}, {"valor": 2, "palabra": "presidente-respeto"}, {"valor": 2, "palabra": "respeto-caluroso"}, {"valor": 2, "palabra": "caluroso-saludo"}, {"valor": 2, "palabra": "saludo-revolucionario"}, {"valor": 2, "palabra": "revolucionario-quiero"}, {"valor": 2, "palabra": "quiero-yulismar"}, {"valor": 2, "palabra": "yulismar-hurtado"}, {"valor": 2, "palabra": "hurtado-titular"}, {"valor": 2, "palabra": "titular-cédula"}, {"valor": 2, "palabra": "cédula-15338112"}, {"valor": 2, "palabra": "15338112-requiere"}, {"valor": 2, "palabra": "requiere-operación"}, {"valor": 2, "palabra": "operación-urgente"}, {"valor": 2, "palabra": "urgente-siguiente"}, {"valor": 2, "palabra": "siguiente-diagnóstico"}, {"valor": 2, "palabra": "diagnóstico-cardiopatia"}, {"valor": 2, "palabra": "cardiopatia-valvular"}, {"valor": 2, "palabra": "valvular-registró"}, {"valor": 2, "palabra": "registró-varios"}, {"valor": 2, "palabra": "varios-respuesta"}, {"valor": 2, "palabra": "respuesta-operación"}, {"valor": 2, "palabra": "operación-costosa"}, {"valor": 2, "palabra": "costosa-cuenta"}, {"valor": 2, "palabra": "cuenta-recursos"}, {"valor": 2, "palabra": "recursos-teléfono"}, {"valor": 2, "palabra": "teléfono-04125434553"}], "VEN - Nicolás Maduro - FB": [{"valor": 80, "palabra": "nicolás-maduro"}, {"valor": 68, "palabra": "república-bolivariana"}, {"valor": 66, "palabra": "bolivariana-venezuela"}, {"valor": 65, "palabra": "chávez-buenos"}, {"valor": 65, "palabra": "presidente-república"}, {"valor": 65, "palabra": "tomaron-cuenta"}, {"valor": 64, "palabra": "buenos-antonio"}, {"valor": 64, "palabra": "antonio-escalona"}, {"valor": 64, "palabra": "escalona-guedez"}, {"valor": 64, "palabra": "guedez-v17640981"}, {"valor": 64, "palabra": "v17640981-solicitud"}, {"valor": 64, "palabra": "solicitud-presidente"}, {"valor": 64, "palabra": "venezuela-indemnización"}, {"valor": 64, "palabra": "indemnización-accidente"}, {"valor": 64, "palabra": "accidente-estando"}, {"valor": 64, "palabra": "estando-servicio"}, {"valor": 64, "palabra": "servicio-momentos"}, {"valor": 64, "palabra": "momentos-cirugía"}, {"valor": 64, "palabra": "cirugía-pierna"}, {"valor": 64, "palabra": "pierna-drenando"}, {"valor": 64, "palabra": "drenando-incurrí"}, {"valor": 64, "palabra": "incurrí-algunas"}, {"valor": 64, "palabra": "algunas-faltas"}, {"valor": 64, "palabra": "faltas-acumulación"}, {"valor": 64, "palabra": "acumulación-expulsadopero"}, {"valor": 64, "palabra": "expulsadopero-tomaron"}, {"valor": 64, "palabra": "cuenta-problema"}, {"valor": 64, "palabra": "problema-dentro"}, {"valor": 64, "palabra": "dentro-fanbno"}, {"valor": 64, "palabra": "fanbno-ningún"}], "VEN - Figuras opositoras - FB": [{"valor": 6, "palabra": "muchas-bendiciones"}, {"valor": 5, "palabra": "edmundo-gonzález"}, {"valor": 4, "palabra": "gonzález-urrutia"}, {"valor": 3, "palabra": "muchas-felicidades"}, {"valor": 2, "palabra": "cuidar-cuidar"}, {"valor": 2, "palabra": "testigos-testigos"}, {"valor": 2, "palabra": "esperar-elecciones"}, {"valor": 2, "palabra": "bendecido-cumpleaños"}, {"valor": 2, "palabra": "cumpleaños-felicidades"}, {"valor": 2, "palabra": "felicidades-muchos"}, {"valor": 2, "palabra": "felicidades-cumpleaños"}, {"valor": 1, "palabra": "bendiga-proteja"}, {"valor": 1, "palabra": "proteja-nuestro"}, {"valor": 1, "palabra": "nuestro-jesucristo"}, {"valor": 1, "palabra": "jesucristo-regale"}, {"valor": 1, "palabra": "regale-muchísima"}, {"valor": 1, "palabra": "muchísima-mejores"}, {"valor": 1, "palabra": "mejores-deseos"}, {"valor": 1, "palabra": "deseos-mónica"}, {"valor": 1, "palabra": "mónica-quiere"}, {"valor": 1, "palabra": "quiere-siempre"}, {"valor": 1, "palabra": "siempre-presente"}, {"valor": 1, "palabra": "presente-abrazo"}, {"valor": 1, "palabra": "abrazo-fuerte"}, {"valor": 1, "palabra": "fuerte-bendiciones"}, {"valor": 1, "palabra": "bendiciones-flamante"}, {"valor": 1, "palabra": "flamante-abuela"}, {"valor": 1, "palabra": "abuela-muchas"}, {"valor": 1, "palabra": "felicidades-bendiga"}, {"valor": 1, "palabra": "bendiga-muchos"}], "VEN - CORINA MACHADO - FB": [{"valor": 34, "palabra": "corina-machado"}, {"valor": 16, "palabra": "edmundo-presidente"}, {"valor": 12, "palabra": "bendiga-corina"}, {"valor": 9, "palabra": "venezuela-corina"}, {"valor": 9, "palabra": "corina-edmundo"}, {"valor": 8, "palabra": "bendiga-venezuela"}, {"valor": 8, "palabra": "bendiga-siempre"}, {"valor": 6, "palabra": "nuestra-libertadora"}, {"valor": 6, "palabra": "machado-edmundo"}, {"valor": 5, "palabra": "adelante-corina"}, {"valor": 5, "palabra": "edmundo-gonzález"}, {"valor": 5, "palabra": "corina-venezuela"}, {"valor": 5, "palabra": "pueblo-venezolano"}, {"valor": 4, "palabra": "venezuela-edmundo"}, {"valor": 4, "palabra": "libertad-venezuela"}, {"valor": 4, "palabra": "libertadora-venezuela"}, {"valor": 4, "palabra": "nuestro-presidente"}, {"valor": 4, "palabra": "nuestra-venezuela"}, {"valor": 3, "palabra": "hospitales-venezuela"}, {"valor": 3, "palabra": "esperanza-pueblo"}, {"valor": 3, "palabra": "maduro-condenado"}, {"valor": 3, "palabra": "presidente-república"}, {"valor": 3, "palabra": "república-venezuela"}, {"valor": 3, "palabra": "corina-libertad"}, {"valor": 3, "palabra": "excelente-palante"}, {"valor": 3, "palabra": "presidente-corina"}, {"valor": 3, "palabra": "gonzález-urrutia"}, {"valor": 3, "palabra": "venezuela-bendiga"}, {"valor": 3, "palabra": "muchas-bendiciones"}, {"valor": 3, "palabra": "machado-esperanza"}]}, "2024-06-26-2024-06-26": {"VEN - Medios adversos - FB": [{"valor": 50, "palabra": "corina-machado"}, {"valor": 44, "palabra": "gabriele-hodges"}, {"valor": 36, "palabra": "edmundo-gonzález"}, {"valor": 33, "palabra": "edmundo-presidente"}, {"valor": 27, "palabra": "amplía-detalles"}, {"valor": 25, "palabra": "estados-unidos"}, {"valor": 23, "palabra": "nicolás-maduro"}, {"valor": 18, "palabra": "gonzález-urrutia"}, {"valor": 17, "palabra": "elecciones-presidenciales"}, {"valor": 17, "palabra": "puente-angostura"}, {"valor": 17, "palabra": "excelente-animador"}, {"valor": 16, "palabra": "intento-estado"}, {"valor": 15, "palabra": "estado-mérida"}, {"valor": 15, "palabra": "cantar-fraude"}, {"valor": 13, "palabra": "brille-perpetua"}, {"valor": 13, "palabra": "corina-cantar"}, {"valor": 12, "palabra": "olvides-suscribirte"}, {"valor": 12, "palabra": "estado-bolivia"}, {"valor": 12, "palabra": "sábado-sensacional"}, {"valor": 12, "palabra": "enlace-continuación"}, {"valor": 12, "palabra": "nombre-continuación"}, {"valor": 11, "palabra": "corina-edmundo"}, {"valor": 10, "palabra": "plataforma-unitaria"}, {"valor": 10, "palabra": "nuestro-contenido"}, {"valor": 9, "palabra": "consejo-nacional"}, {"valor": 9, "palabra": "machado-equipo"}, {"valor": 9, "palabra": "ejército-boliviano"}, {"valor": 9, "palabra": "estado-contra"}, {"valor": 9, "palabra": "presidente-bolivia"}, {"valor": 9, "palabra": "descanso-eterno"}], "VEN - Medios afines - FB": [{"valor": 39, "palabra": "edmundo-presidente"}, {"valor": 28, "palabra": "pueblo-boliviano"}, {"valor": 23, "palabra": "nicolás-maduro"}, {"valor": 21, "palabra": "intento-estado"}, {"valor": 20, "palabra": "edmundo-gonzález"}, {"valor": 18, "palabra": "estado-bolivia"}, {"valor": 15, "palabra": "jajajaja-jajajaja"}, {"valor": 13, "palabra": "pueblo-bolivia"}, {"valor": 13, "palabra": "golpes-estado"}, {"valor": 12, "palabra": "estados-unidos"}, {"valor": 11, "palabra": "presidente-venezuela"}, {"valor": 10, "palabra": "corina-machado"}, {"valor": 10, "palabra": "presidente-edmundo"}, {"valor": 10, "palabra": "presidente-maduro"}, {"valor": 10, "palabra": "fuerzas-armadas"}, {"valor": 10, "palabra": "jajaja-jajaja"}, {"valor": 10, "palabra": "información-ingresa"}, {"valor": 10, "palabra": "ingresa-nuestro"}, {"valor": 10, "palabra": "nuestro-perfil"}, {"valor": 9, "palabra": "julian-assange"}, {"valor": 9, "palabra": "maduro-cuando"}, {"valor": 9, "palabra": "presidente-bolivia"}, {"valor": 8, "palabra": "venezuela-maduro"}, {"valor": 8, "palabra": "estado-contra"}, {"valor": 8, "palabra": "contra-gobierno"}, {"valor": 7, "palabra": "pueblo-venezolano"}, {"valor": 7, "palabra": "militares-golpistas"}, {"valor": 7, "palabra": "gonzález-presidente"}, {"valor": 6, "palabra": "presidente-nicolás"}, {"valor": 6, "palabra": "rafael-urdaneta"}], "VEN - Figuras afines - Ministros FB": [{"valor": 5, "palabra": "pueblo-venezolano"}, {"valor": 4, "palabra": "justicia-contra"}, {"valor": 3, "palabra": "riquezas-venezuela"}, {"valor": 3, "palabra": "derrochando-millones"}, {"valor": 3, "palabra": "millones-dólares"}, {"valor": 3, "palabra": "sumergido-grande"}, {"valor": 3, "palabra": "grande-miseria"}, {"valor": 2, "palabra": "victoria-verdad"}, {"valor": 2, "palabra": "verdad-pueblos"}, {"valor": 2, "palabra": "pueblos-batalla"}, {"valor": 2, "palabra": "batalla-contra"}, {"valor": 2, "palabra": "contra-tiranía"}, {"valor": 2, "palabra": "tiranía-imposiciones"}, {"valor": 2, "palabra": "imposiciones-lawfare"}, {"valor": 2, "palabra": "lawfare-posverdades"}, {"valor": 2, "palabra": "posverdades-satanizaciones"}, {"valor": 2, "palabra": "satanizaciones-espíritus"}, {"valor": 2, "palabra": "espíritus-indoblegables"}, {"valor": 2, "palabra": "indoblegables-valientes"}, {"valor": 2, "palabra": "valientes-assange"}, {"valor": 2, "palabra": "assange-constituye"}, {"valor": 2, "palabra": "constituye-tiempo"}, {"valor": 2, "palabra": "tiempo-horripilantes"}, {"valor": 2, "palabra": "horripilantes-planes"}, {"valor": 2, "palabra": "planes-macabros"}, {"valor": 2, "palabra": "macabros-imperialismo"}, {"valor": 2, "palabra": "imperialismo-anglosajón"}, {"valor": 2, "palabra": "anglosajón-sionista"}, {"valor": 2, "palabra": "sionista-referente"}, {"valor": 2, "palabra": "referente-denuncia"}], "VEN - Nicolás Maduro - FB": [{"valor": 70, "palabra": "bolivariana-venezuela"}, {"valor": 68, "palabra": "república-bolivariana"}, {"valor": 67, "palabra": "chávez-buenos"}, {"valor": 67, "palabra": "buenos-antonio"}, {"valor": 67, "palabra": "antonio-escalona"}, {"valor": 67, "palabra": "escalona-guedez"}, {"valor": 67, "palabra": "guedez-v17640981"}, {"valor": 67, "palabra": "v17640981-solicitud"}, {"valor": 67, "palabra": "solicitud-presidente"}, {"valor": 67, "palabra": "presidente-república"}, {"valor": 67, "palabra": "venezuela-indemnización"}, {"valor": 67, "palabra": "indemnización-accidente"}, {"valor": 67, "palabra": "accidente-estando"}, {"valor": 67, "palabra": "estando-servicio"}, {"valor": 67, "palabra": "servicio-momentos"}, {"valor": 67, "palabra": "momentos-cirugía"}, {"valor": 67, "palabra": "cirugía-pierna"}, {"valor": 67, "palabra": "pierna-drenando"}, {"valor": 67, "palabra": "drenando-incurrí"}, {"valor": 67, "palabra": "incurrí-algunas"}, {"valor": 67, "palabra": "algunas-faltas"}, {"valor": 67, "palabra": "faltas-acumulación"}, {"valor": 67, "palabra": "acumulación-expulsadopero"}, {"valor": 67, "palabra": "expulsadopero-tomaron"}, {"valor": 67, "palabra": "tomaron-cuenta"}, {"valor": 67, "palabra": "cuenta-problema"}, {"valor": 67, "palabra": "problema-dentro"}, {"valor": 67, "palabra": "dentro-fanbno"}, {"valor": 67, "palabra": "fanbno-ningún"}, {"valor": 67, "palabra": "ningún-trabajo"}], "VEN - Figuras opositoras - FB": [{"valor": 15, "palabra": "bendiga-siempre"}, {"valor": 11, "palabra": "hermoso-bendiga"}, {"valor": 7, "palabra": "bendiciones-bendiga"}, {"valor": 7, "palabra": "muchas-bendiciones"}, {"valor": 7, "palabra": "bendiga-proteja"}, {"valor": 6, "palabra": "bendiga-hermoso"}, {"valor": 6, "palabra": "bendiga-bendiga"}, {"valor": 4, "palabra": "bendiga-grandemente"}, {"valor": 4, "palabra": "proteja-siempre"}, {"valor": 4, "palabra": "bendiciones-bendiciones"}, {"valor": 3, "palabra": "hermoso-muchas"}, {"valor": 3, "palabra": "muchas-felicidades"}, {"valor": 3, "palabra": "felicidades-bendiciones"}, {"valor": 3, "palabra": "bendiga-bendiciones"}, {"valor": 3, "palabra": "bendiciones-hermoso"}, {"valor": 3, "palabra": "felicidades-bendiga"}, {"valor": 3, "palabra": "hermoso-bendiciones"}, {"valor": 3, "palabra": "familia-bendiga"}, {"valor": 3, "palabra": "príncipe-bendiga"}, {"valor": 3, "palabra": "bendiciones-infinitas"}, {"valor": 2, "palabra": "enrique-capriles"}, {"valor": 2, "palabra": "edmundo-gonzález"}, {"valor": 2, "palabra": "gonzález-urrutia"}, {"valor": 2, "palabra": "siempre-felicitaciones"}, {"valor": 2, "palabra": "bebito-bendiga"}, {"valor": 2, "palabra": "abrazos-bendiciones"}, {"valor": 2, "palabra": "bendiciones-graduó"}, {"valor": 2, "palabra": "mantenga-sanito"}, {"valor": 2, "palabra": "felicidades-felicidades"}, {"valor": 2, "palabra": "bendiga-felicitaciones"}], "VEN - CORINA MACHADO - FB": [{"valor": 34, "palabra": "corina-machado"}, {"valor": 25, "palabra": "edmundo-gonzález"}, {"valor": 18, "palabra": "gonzález-urrutia"}, {"valor": 17, "palabra": "venezuela-corina"}, {"valor": 14, "palabra": "libertad-venezuela"}, {"valor": 13, "palabra": "edmundo-presidente"}, {"valor": 12, "palabra": "bendiga-siempre"}, {"valor": 12, "palabra": "corina-edmundo"}, {"valor": 11, "palabra": "pueblo-venezolano"}, {"valor": 10, "palabra": "bendiciones-corina"}, {"valor": 10, "palabra": "nuestra-venezuela"}, {"valor": 9, "palabra": "bendiga-venezuela"}, {"valor": 9, "palabra": "corina-bendiga"}, {"valor": 9, "palabra": "bendiga-corina"}, {"valor": 9, "palabra": "venezuela-bendiga"}, {"valor": 8, "palabra": "proteja-siempre"}, {"valor": 8, "palabra": "muchas-bendiciones"}, {"valor": 7, "palabra": "bendiga-grandemente"}, {"valor": 7, "palabra": "corina-pueblo"}, {"valor": 7, "palabra": "venezuela-libertad"}, {"valor": 7, "palabra": "bendiciones-venezuela"}, {"valor": 7, "palabra": "venezuela-venezuela"}, {"valor": 7, "palabra": "urrutia-cuidar"}, {"valor": 7, "palabra": "cuidar-proteger"}, {"valor": 6, "palabra": "fuerza-corina"}, {"valor": 6, "palabra": "gracias-corina"}, {"valor": 6, "palabra": "hospitales-venezuela"}, {"valor": 6, "palabra": "hospital-público"}, {"valor": 6, "palabra": "venezuela-edmundo"}, {"valor": 6, "palabra": "venezuela-tierra"}]}, "2024-06-27-2024-06-27": {"VEN - Medios adversos - FB": [{"valor": 45, "palabra": "edmundo-gonzález"}, {"valor": 32, "palabra": "estados-unidos"}, {"valor": 30, "palabra": "corina-machado"}, {"valor": 29, "palabra": "amplía-detalles"}, {"valor": 23, "palabra": "edmundo-presidente"}, {"valor": 21, "palabra": "elecciones-presidenciales"}, {"valor": 19, "palabra": "intento-estado"}, {"valor": 18, "palabra": "gonzález-urrutia"}, {"valor": 16, "palabra": "nuestra-página"}, {"valor": 15, "palabra": "nicolás-maduro"}, {"valor": 15, "palabra": "equipo-segunda"}, {"valor": 14, "palabra": "pueblo-venezolano"}, {"valor": 13, "palabra": "venezuela-méxico"}, {"valor": 13, "palabra": "noticias-nuestra"}, {"valor": 12, "palabra": "salomón-rondón"}, {"valor": 11, "palabra": "olvides-suscribirte"}, {"valor": 10, "palabra": "cuartos-américa"}, {"valor": 10, "palabra": "plataforma-unitaria"}, {"valor": 10, "palabra": "nuestro-contenido"}, {"valor": 9, "palabra": "nuestro-equipo"}, {"valor": 9, "palabra": "medios-comunicación"}, {"valor": 8, "palabra": "estado-bolivia"}, {"valor": 8, "palabra": "proceso-electoral"}, {"valor": 8, "palabra": "cantar-fraude"}, {"valor": 8, "palabra": "pueblo-quiere"}, {"valor": 7, "palabra": "libertad-expresión"}, {"valor": 7, "palabra": "arriba-venezuela"}, {"valor": 7, "palabra": "hermanos-venezolanos"}, {"valor": 7, "palabra": "venezuela-venezuela"}, {"valor": 7, "palabra": "corina-edmundo"}], "VEN - Medios afines - FB": [{"valor": 29, "palabra": "edmundo-presidente"}, {"valor": 23, "palabra": "nicolás-maduro"}, {"valor": 22, "palabra": "jajajaja-jajajaja"}, {"valor": 21, "palabra": "edmundo-gonzález"}, {"valor": 17, "palabra": "intento-estado"}, {"valor": 13, "palabra": "estado-bolivia"}, {"valor": 12, "palabra": "información-ingresa"}, {"valor": 12, "palabra": "ingresa-nuestro"}, {"valor": 12, "palabra": "nuestro-perfil"}, {"valor": 12, "palabra": "estados-unidos"}, {"valor": 11, "palabra": "venezuela-venezuela"}, {"valor": 10, "palabra": "gonzález-presidente"}, {"valor": 10, "palabra": "pueblo-venezolano"}, {"valor": 10, "palabra": "santiago-estero"}, {"valor": 10, "palabra": "jajaja-jajaja"}, {"valor": 10, "palabra": "presidente-venezuela"}, {"valor": 10, "palabra": "vinotinto-venezuela"}, {"valor": 8, "palabra": "próximo-presidente"}, {"valor": 8, "palabra": "corina-machado"}, {"valor": 8, "palabra": "derecho-humano"}, {"valor": 8, "palabra": "venezuela-carajo"}, {"valor": 7, "palabra": "salomón-rondón"}, {"valor": 7, "palabra": "quiénes-detrás"}, {"valor": 7, "palabra": "detrás-estado"}, {"valor": 7, "palabra": "presidente-nicolás"}, {"valor": 7, "palabra": "elecciones-presidenciales"}, {"valor": 7, "palabra": "telesur-noticias"}, {"valor": 7, "palabra": "arriba-venezuela"}, {"valor": 7, "palabra": "venezuela-edmundo"}, {"valor": 6, "palabra": "bolivia-venezuela"}], "VEN - Figuras afines - Ministros FB": [{"valor": 3, "palabra": "venezuela-patria"}, {"valor": 3, "palabra": "patria-querida"}, {"valor": 3, "palabra": "nuestra-vinotinto"}, {"valor": 2, "palabra": "fundación-correo"}, {"valor": 2, "palabra": "correo-orinoco"}, {"valor": 2, "palabra": "orinoco-libertador"}, {"valor": 2, "palabra": "libertador-bolívar"}, {"valor": 2, "palabra": "bolívar-artillería"}, {"valor": 2, "palabra": "artillería-pensamiento"}, {"valor": 2, "palabra": "pensamiento-compromete"}, {"valor": 2, "palabra": "compromete-ideales"}, {"valor": 2, "palabra": "ideales-independencia"}, {"valor": 2, "palabra": "independencia-soberanía"}, {"valor": 2, "palabra": "soberanía-quedaron"}, {"valor": 2, "palabra": "quedaron-siempre"}, {"valor": 2, "palabra": "siempre-impresos"}, {"valor": 2, "palabra": "impresos-páginas"}, {"valor": 2, "palabra": "páginas-ideales"}, {"valor": 2, "palabra": "ideales-siguen"}, {"valor": 2, "palabra": "siguen-vigentes"}, {"valor": 2, "palabra": "vigentes-complejidades"}, {"valor": 2, "palabra": "complejidades-formas"}, {"valor": 2, "palabra": "formas-tecnologías"}, {"valor": 2, "palabra": "tecnologías-comunicación"}, {"valor": 2, "palabra": "comunicación-contemporánea"}, {"valor": 2, "palabra": "contemporánea-ideales"}, {"valor": 2, "palabra": "ideales-encuentran"}, {"valor": 2, "palabra": "encuentran-expresión"}, {"valor": 2, "palabra": "expresión-venezuela"}, {"valor": 2, "palabra": "venezuela-octavo"}], "VEN - Nicolás Maduro - FB": [{"valor": 134, "palabra": "aumento-aumento"}, {"valor": 112, "palabra": "república-bolivariana"}, {"valor": 111, "palabra": "presidente-república"}, {"valor": 111, "palabra": "bolivariana-venezuela"}, {"valor": 110, "palabra": "chávez-buenos"}, {"valor": 110, "palabra": "buenos-antonio"}, {"valor": 110, "palabra": "antonio-escalona"}, {"valor": 110, "palabra": "escalona-guedez"}, {"valor": 110, "palabra": "guedez-v17640981"}, {"valor": 110, "palabra": "v17640981-solicitud"}, {"valor": 110, "palabra": "solicitud-presidente"}, {"valor": 110, "palabra": "venezuela-indemnización"}, {"valor": 110, "palabra": "indemnización-accidente"}, {"valor": 110, "palabra": "accidente-estando"}, {"valor": 110, "palabra": "estando-servicio"}, {"valor": 110, "palabra": "servicio-momentos"}, {"valor": 110, "palabra": "momentos-cirugía"}, {"valor": 110, "palabra": "cirugía-pierna"}, {"valor": 110, "palabra": "pierna-drenando"}, {"valor": 110, "palabra": "drenando-incurrí"}, {"valor": 110, "palabra": "incurrí-algunas"}, {"valor": 110, "palabra": "algunas-faltas"}, {"valor": 110, "palabra": "faltas-acumulación"}, {"valor": 110, "palabra": "acumulación-expulsadopero"}, {"valor": 110, "palabra": "expulsadopero-tomaron"}, {"valor": 110, "palabra": "tomaron-cuenta"}, {"valor": 110, "palabra": "cuenta-problema"}, {"valor": 110, "palabra": "problema-dentro"}, {"valor": 110, "palabra": "dentro-fanbno"}, {"valor": 110, "palabra": "fanbno-ningún"}], "VEN - Figuras opositoras - FB": [{"valor": 16, "palabra": "hermosas-bendiga"}, {"valor": 13, "palabra": "bellas-bendiga"}, {"valor": 12, "palabra": "hermosas-princesas"}, {"valor": 11, "palabra": "bendiga-siempre"}, {"valor": 10, "palabra": "bendiga-hermosas"}, {"valor": 10, "palabra": "bendiga-bellas"}, {"valor": 7, "palabra": "bendiga-proteja"}, {"valor": 7, "palabra": "proteja-siempre"}, {"valor": 7, "palabra": "preciosas-bendiga"}, {"valor": 6, "palabra": "bendiciones-bendiga"}, {"valor": 6, "palabra": "princesas-bendiga"}, {"valor": 5, "palabra": "bendiciones-bellas"}, {"valor": 5, "palabra": "lindas-bendiga"}, {"valor": 5, "palabra": "bendiga-grandemente"}, {"valor": 4, "palabra": "bendiga-familia"}, {"valor": 4, "palabra": "bendiga-lindas"}, {"valor": 4, "palabra": "siempre-hermosas"}, {"valor": 4, "palabra": "bellas-bendiciones"}, {"valor": 4, "palabra": "bellas-princesas"}, {"valor": 4, "palabra": "belleza-bendiga"}, {"valor": 3, "palabra": "edmundo-presidente"}, {"valor": 3, "palabra": "hermosas-bellas"}, {"valor": 3, "palabra": "bellas-hermosas"}, {"valor": 3, "palabra": "muchas-bendiciones"}, {"valor": 3, "palabra": "lindas-lindas"}, {"valor": 3, "palabra": "princesas-hermosas"}, {"valor": 3, "palabra": "preciosas-bellas"}, {"valor": 3, "palabra": "siempre-bendiga"}, {"valor": 3, "palabra": "grandemente-bellas"}, {"valor": 3, "palabra": "lindas-princesas"}], "VEN - CORINA MACHADO - FB": [{"valor": 32, "palabra": "corina-machado"}, {"valor": 24, "palabra": "jajajaja-jajajaja"}, {"valor": 12, "palabra": "edmundo-gonzález"}, {"valor": 10, "palabra": "edmundo-presidente"}, {"valor": 10, "palabra": "libertad-venezuela"}, {"valor": 10, "palabra": "nuestra-venezuela"}, {"valor": 9, "palabra": "muchas-bendiciones"}, {"valor": 9, "palabra": "corina-edmundo"}, {"valor": 9, "palabra": "venezuela-edmundo"}, {"valor": 8, "palabra": "venezuela-venezuela"}, {"valor": 8, "palabra": "bendiga-siempre"}, {"valor": 8, "palabra": "venezuela-corina"}, {"valor": 8, "palabra": "arriba-venezuela"}, {"valor": 7, "palabra": "venezuela-bendiga"}, {"valor": 7, "palabra": "vinotinto-corina"}, {"valor": 7, "palabra": "vinotinto-venezuela"}, {"valor": 6, "palabra": "bendiga-venezuela"}, {"valor": 6, "palabra": "pueblo-venezolano"}, {"valor": 6, "palabra": "grande-venezuela"}, {"valor": 5, "palabra": "edmundo-venezuela"}, {"valor": 5, "palabra": "próximo-presidente"}, {"valor": 5, "palabra": "contigo-corina"}, {"valor": 5, "palabra": "gonzález-urrutia"}, {"valor": 5, "palabra": "venezuela-estamos"}, {"valor": 5, "palabra": "presidente-venezuela"}, {"valor": 4, "palabra": "presidenta-venezuela"}, {"valor": 4, "palabra": "bendiciones-corina"}, {"valor": 4, "palabra": "corina-venezuela"}, {"valor": 4, "palabra": "bendiga-grandemente"}, {"valor": 4, "palabra": "bendiga-corina"}]}, "2024-06-28-2024-06-28": {"VEN - Medios adversos - FB": [{"valor": 49, "palabra": "corina-machado"}, {"valor": 35, "palabra": "edmundo-gonzález"}, {"valor": 29, "palabra": "edmundo-presidente"}, {"valor": 29, "palabra": "colombia-colombia"}, {"valor": 21, "palabra": "nicolás-maduro"}, {"valor": 19, "palabra": "estados-unidos"}, {"valor": 19, "palabra": "gabriele-hodges"}, {"valor": 17, "palabra": "gonzález-urrutia"}, {"valor": 17, "palabra": "ganando-colombia"}, {"valor": 16, "palabra": "amplía-detalles"}, {"valor": 13, "palabra": "cantar-fraude"}, {"valor": 13, "palabra": "elecciones-presidenciales"}, {"valor": 12, "palabra": "corina-cantar"}, {"valor": 11, "palabra": "colombia-ganando"}, {"valor": 10, "palabra": "jajajaja-jajajaja"}, {"valor": 9, "palabra": "consejo-nacional"}, {"valor": 9, "palabra": "nacional-electoral"}, {"valor": 8, "palabra": "debate-presidencial"}, {"valor": 8, "palabra": "derechos-humanos"}, {"valor": 8, "palabra": "opositora-corina"}, {"valor": 8, "palabra": "presidente-venezuela"}, {"valor": 8, "palabra": "gracias-gabriele"}, {"valor": 7, "palabra": "primer-debate"}, {"valor": 7, "palabra": "plataforma-unitaria"}, {"valor": 7, "palabra": "cuartos-américa"}, {"valor": 7, "palabra": "gobierno-nicolás"}, {"valor": 7, "palabra": "intento-estado"}, {"valor": 7, "palabra": "olvides-suscribirte"}, {"valor": 7, "palabra": "selección-colombia"}, {"valor": 7, "palabra": "ganaron-porque"}], "VEN - Medios afines - FB": [{"valor": 29, "palabra": "nicolás-maduro"}, {"valor": 15, "palabra": "corina-machado"}, {"valor": 14, "palabra": "ingresa-nuestro"}, {"valor": 14, "palabra": "nuestro-perfil"}, {"valor": 13, "palabra": "información-ingresa"}, {"valor": 13, "palabra": "edmundo-presidente"}, {"valor": 12, "palabra": "edmundo-gonzález"}, {"valor": 11, "palabra": "presidente-nicolás"}, {"valor": 10, "palabra": "estados-unidos"}, {"valor": 9, "palabra": "jajaja-jajaja"}, {"valor": 8, "palabra": "premio-nacional"}, {"valor": 8, "palabra": "nacional-periodismo"}, {"valor": 7, "palabra": "corina-edmundo"}, {"valor": 7, "palabra": "pueblo-venezolano"}, {"valor": 7, "palabra": "venezuela-venezuela"}, {"valor": 7, "palabra": "jajajaja-jajajaja"}, {"valor": 6, "palabra": "simulacro-electoral"}, {"valor": 5, "palabra": "victoria-cecilia"}, {"valor": 5, "palabra": "cecilia-bernal"}, {"valor": 5, "palabra": "bernal-aguilar"}, {"valor": 5, "palabra": "maduro-venezuela"}, {"valor": 5, "palabra": "elecciones-presidenciales"}, {"valor": 5, "palabra": "_________-suscribete"}, {"valor": 5, "palabra": "suscribete-nuestro"}, {"valor": 5, "palabra": "nuestro-respaldo"}, {"valor": 5, "palabra": "respaldo-_________"}, {"valor": 5, "palabra": "_________-instagram"}, {"valor": 5, "palabra": "instagram-facebook"}, {"valor": 5, "palabra": "facebook-twitch"}, {"valor": 5, "palabra": "twitch-tiktok"}], "VEN - Figuras afines - Ministros FB": [{"valor": 2, "palabra": "municipio-estado"}, {"valor": 2, "palabra": "estado-carabobo"}, {"valor": 2, "palabra": "nuestro-pueblo"}, {"valor": 2, "palabra": "pueblo-zuliano"}, {"valor": 2, "palabra": "libertador-bolívar"}, {"valor": 2, "palabra": "oficiales-tropas"}, {"valor": 2, "palabra": "tropas-profesionales"}, {"valor": 2, "palabra": "circuitos-comunales"}, {"valor": 1, "palabra": "acciones-negativas"}, {"valor": 1, "palabra": "negativas-viscerales"}, {"valor": 1, "palabra": "viscerales-esperanza"}, {"valor": 1, "palabra": "esperanza-reunimos"}, {"valor": 1, "palabra": "reunimos-nuestro"}, {"valor": 1, "palabra": "nuestro-equipo"}, {"valor": 1, "palabra": "equipo-trabajo"}, {"valor": 1, "palabra": "trabajo-municipio"}, {"valor": 1, "palabra": "carabobo-objetivo"}, {"valor": 1, "palabra": "objetivo-revisar"}, {"valor": 1, "palabra": "revisar-procedimiento"}, {"valor": 1, "palabra": "procedimiento-realizado"}, {"valor": 1, "palabra": "realizado-nuestra"}, {"valor": 1, "palabra": "nuestra-maquinaria"}, {"valor": 1, "palabra": "maquinaria-electoral"}, {"valor": 1, "palabra": "electoral-organizar"}, {"valor": 1, "palabra": "organizar-movilizaciones"}, {"valor": 1, "palabra": "movilizaciones-celebraremos"}, {"valor": 1, "palabra": "celebraremos-nuestro"}, {"valor": 1, "palabra": "pueblo-respaldo"}, {"valor": 1, "palabra": "respaldo-nuestro"}, {"valor": 1, "palabra": "nuestro-hermano"}], "VEN - Nicolás Maduro - FB": [{"valor": 65, "palabra": "nicolás-maduro"}, {"valor": 64, "palabra": "república-bolivariana"}, {"valor": 64, "palabra": "bolivariana-venezuela"}, {"valor": 63, "palabra": "presidente-república"}, {"valor": 62, "palabra": "chávez-buenos"}, {"valor": 62, "palabra": "buenos-antonio"}, {"valor": 62, "palabra": "antonio-escalona"}, {"valor": 62, "palabra": "escalona-guedez"}, {"valor": 62, "palabra": "guedez-v17640981"}, {"valor": 62, "palabra": "v17640981-solicitud"}, {"valor": 62, "palabra": "solicitud-presidente"}, {"valor": 62, "palabra": "venezuela-indemnización"}, {"valor": 62, "palabra": "indemnización-accidente"}, {"valor": 62, "palabra": "accidente-estando"}, {"valor": 62, "palabra": "estando-servicio"}, {"valor": 62, "palabra": "servicio-momentos"}, {"valor": 62, "palabra": "momentos-cirugía"}, {"valor": 62, "palabra": "cirugía-pierna"}, {"valor": 62, "palabra": "pierna-drenando"}, {"valor": 62, "palabra": "drenando-incurrí"}, {"valor": 62, "palabra": "incurrí-algunas"}, {"valor": 62, "palabra": "algunas-faltas"}, {"valor": 62, "palabra": "faltas-acumulación"}, {"valor": 62, "palabra": "acumulación-expulsadopero"}, {"valor": 62, "palabra": "expulsadopero-tomaron"}, {"valor": 62, "palabra": "tomaron-cuenta"}, {"valor": 62, "palabra": "cuenta-problema"}, {"valor": 62, "palabra": "problema-dentro"}, {"valor": 62, "palabra": "dentro-fanbno"}, {"valor": 62, "palabra": "fanbno-ningún"}], "VEN - Figuras opositoras - FB": [{"valor": 8, "palabra": "edmundo-gonzález"}, {"valor": 7, "palabra": "gonzález-urrutia"}, {"valor": 6, "palabra": "hermosas-bendiga"}, {"valor": 4, "palabra": "lindas-bendiga"}, {"valor": 4, "palabra": "bendiga-hermosas"}, {"valor": 4, "palabra": "bendiga-proteja"}, {"valor": 3, "palabra": "princesas-bendiga"}, {"valor": 3, "palabra": "bendiga-siempre"}, {"valor": 2, "palabra": "representa-edmundo"}, {"valor": 2, "palabra": "edmundo-presidente"}, {"valor": 2, "palabra": "hermosa-bendiga"}, {"valor": 2, "palabra": "bendiga-muchos"}, {"valor": 2, "palabra": "muchos-bellas"}, {"valor": 2, "palabra": "bellas-bendiga"}, {"valor": 2, "palabra": "gregorio-hernández"}, {"valor": 2, "palabra": "proteja-hermosas"}, {"valor": 2, "palabra": "hermosas-hermosas"}, {"valor": 2, "palabra": "capriles-bendiga"}, {"valor": 2, "palabra": "hermosa-princesa"}, {"valor": 2, "palabra": "princesa-bendiga"}, {"valor": 2, "palabra": "hermosas-princesas"}, {"valor": 2, "palabra": "bendiga-familia"}, {"valor": 2, "palabra": "felicidades-capriles"}, {"valor": 2, "palabra": "bendiga-princesas"}, {"valor": 1, "palabra": "compañía-nuestro"}, {"valor": 1, "palabra": "nuestro-candidato"}, {"valor": 1, "palabra": "candidato-juntos"}, {"valor": 1, "palabra": "juntos-fuertes"}, {"valor": 1, "palabra": "fuertes-hermosas"}, {"valor": 1, "palabra": "bendiga-grande"}], "VEN - CORINA MACHADO - FB": [{"valor": 29, "palabra": "corina-machado"}, {"valor": 17, "palabra": "edmundo-presidente"}, {"valor": 14, "palabra": "venezuela-corina"}, {"valor": 12, "palabra": "corina-bendiga"}, {"valor": 11, "palabra": "muchas-bendiciones"}, {"valor": 11, "palabra": "bendiga-siempre"}, {"valor": 10, "palabra": "bendiga-venezuela"}, {"valor": 10, "palabra": "corina-edmundo"}, {"valor": 10, "palabra": "venezuela-bendiga"}, {"valor": 10, "palabra": "libertad-libertad"}, {"valor": 9, "palabra": "edmundo-gonzález"}, {"valor": 9, "palabra": "bendiga-corina"}, {"valor": 8, "palabra": "gracias-corina"}, {"valor": 8, "palabra": "pueblo-venezuela"}, {"valor": 7, "palabra": "edmundo-venezuela"}, {"valor": 7, "palabra": "corina-venezuela"}, {"valor": 7, "palabra": "estamos-contigo"}, {"valor": 7, "palabra": "gonzález-urrutia"}, {"valor": 7, "palabra": "venezuela-nombre"}, {"valor": 7, "palabra": "corina-bendiciones"}, {"valor": 7, "palabra": "bendiga-bendiga"}, {"valor": 6, "palabra": "libertad-bendiga"}, {"valor": 6, "palabra": "nuestra-libertadora"}, {"valor": 6, "palabra": "bendiga-pueblo"}, {"valor": 6, "palabra": "libertad-venezuela"}, {"valor": 6, "palabra": "nuestra-venezuela"}, {"valor": 5, "palabra": "venezuela-bendiciones"}, {"valor": 5, "palabra": "bendiciones-edmundo"}, {"valor": 5, "palabra": "bendiciones-corina"}, {"valor": 5, "palabra": "hermanos-venezolanos"}]}, "2024-06-29-2024-06-29": {"VEN - Medios adversos - FB": [{"valor": 43, "palabra": "corina-machado"}, {"valor": 28, "palabra": "edmundo-gonzález"}, {"valor": 22, "palabra": "amplía-detalles"}, {"valor": 20, "palabra": "edmundo-presidente"}, {"valor": 19, "palabra": "gonzález-urrutia"}, {"valor": 18, "palabra": "jajajaja-jajajaja"}, {"valor": 17, "palabra": "nicolás-maduro"}, {"valor": 16, "palabra": "gabriele-hodges"}, {"valor": 13, "palabra": "corina-edmundo"}, {"valor": 11, "palabra": "estados-unidos"}, {"valor": 11, "palabra": "elecciones-presidenciales"}, {"valor": 10, "palabra": "plataforma-unitaria"}, {"valor": 10, "palabra": "consejo-nacional"}, {"valor": 10, "palabra": "nacional-electoral"}, {"valor": 9, "palabra": "eduardo-serrano"}, {"valor": 8, "palabra": "edmundo-corina"}, {"valor": 8, "palabra": "unitaria-democrática"}, {"valor": 8, "palabra": "mossack-fonseca"}, {"valor": 8, "palabra": "firmar-acuerdo"}, {"valor": 8, "palabra": "señora-gabriele"}, {"valor": 7, "palabra": "derechos-humanos"}, {"valor": 6, "palabra": "papeles-panamá"}, {"valor": 6, "palabra": "opositora-corina"}, {"valor": 6, "palabra": "candidato-presidencial"}, {"valor": 6, "palabra": "participar-simulacro"}, {"valor": 6, "palabra": "vengan-conmigo"}, {"valor": 6, "palabra": "freddy-bernal"}, {"valor": 6, "palabra": "pueblo-venezolano"}, {"valor": 6, "palabra": "serrano-tiktok"}, {"valor": 5, "palabra": "fernando-batista"}], "VEN - Medios afines - FB": [{"valor": 96, "palabra": "edmundo-presidente"}, {"valor": 42, "palabra": "edmundo-gonzález"}, {"valor": 28, "palabra": "presidente-edmundo"}, {"valor": 23, "palabra": "corina-machado"}, {"valor": 21, "palabra": "nicolás-maduro"}, {"valor": 20, "palabra": "presidente-venezuela"}, {"valor": 14, "palabra": "corina-edmundo"}, {"valor": 13, "palabra": "simulacro-electoral"}, {"valor": 12, "palabra": "presidente-maduro"}, {"valor": 12, "palabra": "gonzález-presidente"}, {"valor": 12, "palabra": "venezuela-edmundo"}, {"valor": 11, "palabra": "jajaja-jajaja"}, {"valor": 11, "palabra": "gonzález-urrutia"}, {"valor": 11, "palabra": "edmundo-corina"}, {"valor": 10, "palabra": "presidente-nicolás"}, {"valor": 10, "palabra": "pueblo-venezolano"}, {"valor": 10, "palabra": "edmundo-edmundo"}, {"valor": 10, "palabra": "jajajaja-jajajaja"}, {"valor": 9, "palabra": "centros-votación"}, {"valor": 9, "palabra": "también-rebeldía"}, {"valor": 9, "palabra": "rebeldía-puesssssss"}, {"valor": 9, "palabra": "puesssssss-venezuela"}, {"valor": 9, "palabra": "venezuela-decidir"}, {"valor": 9, "palabra": "decidir-venezuela"}, {"valor": 9, "palabra": "venezuela-decente"}, {"valor": 9, "palabra": "decente-bonita"}, {"valor": 9, "palabra": "bonita-regreso"}, {"valor": 9, "palabra": "regreso-nuestros"}, {"valor": 9, "palabra": "nuestros-compatriotas"}, {"valor": 9, "palabra": "compatriotas-hacemos"}], "VEN - Figuras afines - Ministros FB": [{"valor": 2, "palabra": "patria-libertadores"}, {"valor": 2, "palabra": "libertadores-refleja"}, {"valor": 2, "palabra": "refleja-destrucción"}, {"valor": 2, "palabra": "destrucción-sistema"}, {"valor": 2, "palabra": "sistema-seguridad"}, {"valor": 2, "palabra": "seguridad-familia"}, {"valor": 2, "palabra": "familia-manera"}, {"valor": 2, "palabra": "manera-gratuita"}, {"valor": 2, "palabra": "gratuita-traicionaría"}, {"valor": 2, "palabra": "traicionaría-ratifica"}, {"valor": 2, "palabra": "ratifica-escoria"}, {"valor": 2, "palabra": "escoria-castro"}, {"valor": 2, "palabra": "castro-maduro"}, {"valor": 2, "palabra": "maduro-dinero"}, {"valor": 2, "palabra": "dinero-vulgar"}, {"valor": 2, "palabra": "vulgar-ratero"}, {"valor": 2, "palabra": "ratero-robado"}, {"valor": 2, "palabra": "robado-pueblo"}, {"valor": 2, "palabra": "pueblo-venezolano"}, {"valor": 2, "palabra": "candidato-patria"}, {"valor": 1, "palabra": "misión-venezuela"}, {"valor": 1, "palabra": "venezuela-recupera"}, {"valor": 1, "palabra": "recupera-auditorio"}, {"valor": 1, "palabra": "auditorio-uneartebarquisimeto"}, {"valor": 1, "palabra": "uneartebarquisimeto-vísperas"}, {"valor": 1, "palabra": "vísperas-tercer"}, {"valor": 1, "palabra": "tercer-capítulo"}, {"valor": 1, "palabra": "capítulo-festival"}, {"valor": 1, "palabra": "festival-mundial"}, {"valor": 1, "palabra": "mundial-venezuela"}], "VEN - Nicolás Maduro - FB": [{"valor": 96, "palabra": "nicolás-maduro"}, {"valor": 48, "palabra": "presidente-nicolás"}, {"valor": 43, "palabra": "república-bolivariana"}, {"valor": 42, "palabra": "bolivariana-venezuela"}, {"valor": 41, "palabra": "presidente-república"}, {"valor": 34, "palabra": "presidente-maduro"}, {"valor": 28, "palabra": "chávez-buenos"}, {"valor": 28, "palabra": "buenos-antonio"}, {"valor": 28, "palabra": "antonio-escalona"}, {"valor": 28, "palabra": "escalona-guedez"}, {"valor": 28, "palabra": "guedez-v17640981"}, {"valor": 28, "palabra": "v17640981-solicitud"}, {"valor": 28, "palabra": "solicitud-presidente"}, {"valor": 28, "palabra": "venezuela-indemnización"}, {"valor": 28, "palabra": "indemnización-accidente"}, {"valor": 28, "palabra": "accidente-estando"}, {"valor": 28, "palabra": "estando-servicio"}, {"valor": 28, "palabra": "servicio-momentos"}, {"valor": 28, "palabra": "momentos-cirugía"}, {"valor": 28, "palabra": "cirugía-pierna"}, {"valor": 28, "palabra": "pierna-drenando"}, {"valor": 28, "palabra": "drenando-incurrí"}, {"valor": 28, "palabra": "incurrí-algunas"}, {"valor": 28, "palabra": "algunas-faltas"}, {"valor": 28, "palabra": "faltas-acumulación"}, {"valor": 28, "palabra": "acumulación-expulsadopero"}, {"valor": 28, "palabra": "expulsadopero-tomaron"}, {"valor": 28, "palabra": "tomaron-cuenta"}, {"valor": 28, "palabra": "cuenta-problema"}, {"valor": 28, "palabra": "problema-dentro"}], "VEN - Figuras opositoras - FB": [{"valor": 7, "palabra": "bellos-bendiga"}, {"valor": 4, "palabra": "bendiga-siempre"}, {"valor": 3, "palabra": "fuerte-abrazo"}, {"valor": 3, "palabra": "felicidades-bellos"}, {"valor": 3, "palabra": "abrazo-felicidades"}, {"valor": 3, "palabra": "muchas-bendiciones"}, {"valor": 2, "palabra": "muchas-felicidades"}, {"valor": 2, "palabra": "bendiciones-nietos"}, {"valor": 2, "palabra": "bellos-saludos"}, {"valor": 2, "palabra": "bendiga-grandemente"}, {"valor": 2, "palabra": "bellos-abuelo"}, {"valor": 1, "palabra": "estamos-haciendo"}, {"valor": 1, "palabra": "haciendo-seguimos"}, {"valor": 1, "palabra": "seguimos-trabajando"}, {"valor": 1, "palabra": "trabajando-preciosas"}, {"valor": 1, "palabra": "preciosas-campeonas"}, {"valor": 1, "palabra": "campeonas-encanta"}, {"valor": 1, "palabra": "encanta-estaba"}, {"valor": 1, "palabra": "estaba-esperando"}, {"valor": 1, "palabra": "esperando-acompañando"}, {"valor": 1, "palabra": "acompañando-nuestro"}, {"valor": 1, "palabra": "nuestro-candidato"}, {"valor": 1, "palabra": "candidato-edmundo"}, {"valor": 1, "palabra": "edmundo-gonzález"}, {"valor": 1, "palabra": "gonzález-urrutia"}, {"valor": 1, "palabra": "urrutia-estado"}, {"valor": 1, "palabra": "estado-miranda"}, {"valor": 1, "palabra": "miranda-haciendo"}, {"valor": 1, "palabra": "haciendo-trabajo"}, {"valor": 1, "palabra": "trabajo-hormiguita"}], "VEN - CORINA MACHADO - FB": [{"valor": 27, "palabra": "corina-machado"}, {"valor": 12, "palabra": "pueblo-venezolano"}, {"valor": 11, "palabra": "bendiga-siempre"}, {"valor": 11, "palabra": "edmundo-presidente"}, {"valor": 10, "palabra": "edmundo-gonzález"}, {"valor": 8, "palabra": "bendiga-corina"}, {"valor": 8, "palabra": "muchas-bendiciones"}, {"valor": 7, "palabra": "presidente-venezuela"}, {"valor": 7, "palabra": "venezuela-libertad"}, {"valor": 7, "palabra": "libertad-venezuela"}, {"valor": 6, "palabra": "nuestra-libertadora"}, {"valor": 6, "palabra": "bendiga-proteja"}, {"valor": 6, "palabra": "proteja-siempre"}, {"valor": 6, "palabra": "libertad-carajo"}, {"valor": 6, "palabra": "libertadora-venezuela"}, {"valor": 6, "palabra": "venezuela-corina"}, {"valor": 6, "palabra": "coronel-patria"}, {"valor": 5, "palabra": "corina-edmundo"}, {"valor": 5, "palabra": "venezuela-bendiga"}, {"valor": 5, "palabra": "bendiga-venezuela"}, {"valor": 5, "palabra": "gonzález-urrutia"}, {"valor": 5, "palabra": "pueblo-quiere"}, {"valor": 4, "palabra": "fuerza-corina"}, {"valor": 4, "palabra": "pueblo-venezuela"}, {"valor": 4, "palabra": "corina-gracias"}, {"valor": 4, "palabra": "libertad-bendiga"}, {"valor": 4, "palabra": "gloria-pueblo"}, {"valor": 4, "palabra": "nuestro-jesucristo"}, {"valor": 4, "palabra": "libertad-grande"}, {"valor": 4, "palabra": "nombre-venezuela"}]}, "2024-06-30-2024-06-30": {"VEN - Medios adversos - FB": [{"valor": 41, "palabra": "jajajaja-jajajaja"}, {"valor": 40, "palabra": "venezuela-jamaica"}, {"valor": 40, "palabra": "simulacro-electoral"}, {"valor": 37, "palabra": "edmundo-gonzález"}, {"valor": 33, "palabra": "venezuela-venezuela"}, {"valor": 23, "palabra": "edmundo-presidente"}, {"valor": 23, "palabra": "centros-votación"}, {"valor": 21, "palabra": "amplía-detalles"}, {"valor": 20, "palabra": "elecciones-presidenciales"}, {"valor": 19, "palabra": "jajaja-jajaja"}, {"valor": 18, "palabra": "consejo-nacional"}, {"valor": 18, "palabra": "nacional-electoral"}, {"valor": 18, "palabra": "jamaica-venezuela"}, {"valor": 17, "palabra": "corina-machado"}, {"valor": 15, "palabra": "estados-unidos"}, {"valor": 15, "palabra": "gonzález-urrutia"}, {"valor": 11, "palabra": "vinotinto-venezuela"}, {"valor": 11, "palabra": "presidenciales-próximo"}, {"valor": 11, "palabra": "centro-votación"}, {"valor": 11, "palabra": "cantar-fraude"}, {"valor": 10, "palabra": "nicolás-maduro"}, {"valor": 9, "palabra": "agrupación-nacional"}, {"valor": 9, "palabra": "arriba-venezuela"}, {"valor": 9, "palabra": "corina-cantar"}, {"valor": 8, "palabra": "primera-vuelta"}, {"valor": 8, "palabra": "mayoría-absoluta"}, {"valor": 8, "palabra": "salomón-rondón"}, {"valor": 8, "palabra": "plataforma-unitaria"}, {"valor": 8, "palabra": "electoral-domingo"}, {"valor": 8, "palabra": "fuerzas-armadas"}], "VEN - Medios afines - FB": [{"valor": 69, "palabra": "edmundo-presidente"}, {"valor": 61, "palabra": "simulacro-electoral"}, {"valor": 50, "palabra": "edmundo-gonzález"}, {"valor": 26, "palabra": "corina-machado"}, {"valor": 25, "palabra": "gonzález-urrutia"}, {"valor": 24, "palabra": "presidente-venezuela"}, {"valor": 21, "palabra": "participar-simulacro"}, {"valor": 20, "palabra": "centros-votación"}, {"valor": 18, "palabra": "amplía-información"}, {"valor": 17, "palabra": "venezuela-edmundo"}, {"valor": 15, "palabra": "gonzález-presidente"}, {"valor": 15, "palabra": "urrutia-presidente"}, {"valor": 14, "palabra": "jajajaja-jajajaja"}, {"valor": 13, "palabra": "nacional-electoral"}, {"valor": 12, "palabra": "consejo-nacional"}, {"valor": 12, "palabra": "pueblo-venezolano"}, {"valor": 12, "palabra": "nicolás-maduro"}, {"valor": 11, "palabra": "presidente-edmundo"}, {"valor": 11, "palabra": "centros-electorales"}, {"valor": 11, "palabra": "información-nuestra"}, {"valor": 11, "palabra": "nuestra-página"}, {"valor": 11, "palabra": "página-noticierovenevisionnet"}, {"valor": 10, "palabra": "corina-edmundo"}, {"valor": 10, "palabra": "elecciones-presidenciales"}, {"valor": 10, "palabra": "activa-sonido"}, {"valor": 10, "palabra": "venezuela-maduro"}, {"valor": 9, "palabra": "estados-unidos"}, {"valor": 8, "palabra": "simulacro-domingo"}, {"valor": 8, "palabra": "presidente-maduro"}, {"valor": 8, "palabra": "jajaja-jajaja"}], "VEN - Figuras afines - Ministros FB": [{"valor": 3, "palabra": "simulacro-electoral"}, {"valor": 2, "palabra": "elecciones-presidenciales"}, {"valor": 2, "palabra": "cultores-artistas"}, {"valor": 2, "palabra": "artistas-creadores"}, {"valor": 2, "palabra": "creadores-creadoras"}, {"valor": 2, "palabra": "creadoras-también"}, {"valor": 2, "palabra": "también-participan"}, {"valor": 2, "palabra": "domingo-proyecta"}, {"valor": 2, "palabra": "proyecta-jornada"}, {"valor": 2, "palabra": "jornada-temprano"}, {"valor": 2, "palabra": "temprano-pueblo"}, {"valor": 2, "palabra": "pueblo-revolucionario"}, {"valor": 2, "palabra": "revolucionario-centros"}, {"valor": 2, "palabra": "centros-electorales"}, {"valor": 2, "palabra": "nuestros-electoral"}, {"valor": 2, "palabra": "electoral-1x10x7"}, {"valor": 2, "palabra": "1x10x7-movimiento"}, {"valor": 2, "palabra": "movimiento-social"}, {"valor": 2, "palabra": "facilito-facilito"}, {"valor": 2, "palabra": "centro-votación"}, {"valor": 2, "palabra": "nicolás-maduro"}, {"valor": 1, "palabra": "escuela-ciudad"}, {"valor": 1, "palabra": "ciudad-maturín"}, {"valor": 1, "palabra": "maturín-barrio"}, {"valor": 1, "palabra": "barrio-parroquia"}, {"valor": 1, "palabra": "parroquia-municipio"}, {"valor": 1, "palabra": "municipio-iribarren"}, {"valor": 1, "palabra": "iribarren-estado"}, {"valor": 1, "palabra": "estado-participar"}, {"valor": 1, "palabra": "participar-elecciones"}], "VEN - Nicolás Maduro - FB": [{"valor": 32, "palabra": "nicolás-maduro"}, {"valor": 14, "palabra": "presidente-nicolás"}, {"valor": 11, "palabra": "presidente-maduro"}, {"valor": 8, "palabra": "maduro-venezuela"}, {"valor": 7, "palabra": "victoria-siempre"}, {"valor": 7, "palabra": "bendiga-presidente"}, {"valor": 7, "palabra": "maduro-maduro"}, {"valor": 6, "palabra": "presidente-república"}, {"valor": 6, "palabra": "república-bolivariana"}, {"valor": 6, "palabra": "bolivariana-venezuela"}, {"valor": 6, "palabra": "venezuela-invicta"}, {"valor": 6, "palabra": "nuestro-presidente"}, {"valor": 6, "palabra": "revolución-bolivariana"}, {"valor": 6, "palabra": "victoria-victoria"}, {"valor": 6, "palabra": "muchas-felicidades"}, {"valor": 6, "palabra": "edmundo-gonzález"}, {"valor": 5, "palabra": "harina-amarilla"}, {"valor": 5, "palabra": "bendiciones-presidente"}, {"valor": 4, "palabra": "decide-tarjeton"}, {"valor": 4, "palabra": "tarjeton-electoral"}, {"valor": 4, "palabra": "electoral-nicolás"}, {"valor": 4, "palabra": "siempre-venceremos"}, {"valor": 4, "palabra": "corina-machado"}, {"valor": 4, "palabra": "maduro-títeres"}, {"valor": 4, "palabra": "títeres-controlados"}, {"valor": 4, "palabra": "controlados-miserable"}, {"valor": 4, "palabra": "miserable-comida"}, {"valor": 4, "palabra": "comida-vencida"}, {"valor": 4, "palabra": "comandante-chávez"}, {"valor": 4, "palabra": "arriba-venezuela"}], "VEN - Figuras opositoras - FB": [{"valor": 3, "palabra": "vinotinto-venezuela"}, {"valor": 3, "palabra": "venezuela-edmundo"}, {"valor": 2, "palabra": "felicidades-bendiciones"}, {"valor": 2, "palabra": "edmundo-gonzález"}, {"valor": 2, "palabra": "gonzález-urrutia"}, {"valor": 2, "palabra": "gracias-vinotinto"}, {"valor": 2, "palabra": "maduro-venezuela"}, {"valor": 2, "palabra": "tendremos-venezuela"}, {"valor": 2, "palabra": "segunda-patria"}, {"valor": 2, "palabra": "venezuela-venezolanos"}, {"valor": 2, "palabra": "venezolanos-queremos"}, {"valor": 2, "palabra": "simulacro-porque"}, {"valor": 2, "palabra": "testigos-miembros"}, {"valor": 2, "palabra": "cifras-consejo"}, {"valor": 2, "palabra": "consejo-nacional"}, {"valor": 2, "palabra": "nacional-electoral"}, {"valor": 2, "palabra": "oposición-participo"}, {"valor": 2, "palabra": "cuidar-cuidar"}, {"valor": 2, "palabra": "testigos-testigos"}, {"valor": 2, "palabra": "edmundo-edmundo"}, {"valor": 2, "palabra": "esperanza-venezuela"}, {"valor": 1, "palabra": "recordar-tantos"}, {"valor": 1, "palabra": "tantos-momentos"}, {"valor": 1, "palabra": "momentos-maravillosos"}, {"valor": 1, "palabra": "maravillosos-vividos"}, {"valor": 1, "palabra": "vividos-saludos"}, {"valor": 1, "palabra": "saludos-amigos"}, {"valor": 1, "palabra": "amigos-saludos"}, {"valor": 1, "palabra": "saludos-familia"}, {"valor": 1, "palabra": "familia-cumaná"}], "VEN - CORINA MACHADO - FB": [{"valor": 34, "palabra": "corina-machado"}, {"valor": 14, "palabra": "edmundo-gonzález"}, {"valor": 10, "palabra": "libertad-venezuela"}, {"valor": 9, "palabra": "nuestra-venezuela"}, {"valor": 7, "palabra": "venezuela-vinotinto"}, {"valor": 6, "palabra": "venezuela-libertad"}, {"valor": 5, "palabra": "gonzález-urrutia"}, {"valor": 5, "palabra": "bendiga-venezuela"}, {"valor": 4, "palabra": "corina-edmundo"}, {"valor": 4, "palabra": "venezuela-también"}, {"valor": 4, "palabra": "venezuela-venezuela"}, {"valor": 4, "palabra": "nombre-poderoso"}, {"valor": 4, "palabra": "presidente-venezuela"}, {"valor": 4, "palabra": "machado-presidente"}, {"valor": 4, "palabra": "corina-venezuela"}, {"valor": 4, "palabra": "venezuela-victoria"}, {"valor": 4, "palabra": "bendiga-corina"}, {"valor": 4, "palabra": "faltas-corina"}, {"valor": 4, "palabra": "vinotinto-venezuela"}, {"valor": 4, "palabra": "urrutia-presidente"}, {"valor": 4, "palabra": "estamos-contigo"}, {"valor": 4, "palabra": "presidenta-venezuela"}, {"valor": 4, "palabra": "venezuela-estamos"}, {"valor": 4, "palabra": "grande-venezuela"}, {"valor": 4, "palabra": "venezuela-edmundo"}, {"valor": 4, "palabra": "venezuela-corina"}, {"valor": 3, "palabra": "venezuela-pronto"}, {"valor": 3, "palabra": "nuestra-nación"}, {"valor": 3, "palabra": "venezuela-ganamos"}, {"valor": 3, "palabra": "gonzález-presidente"}]}}